hrflow_importer/__init__.py
hrflow_importer/import_cli.py
hrflow_importer/importer/__init__.py
hrflow_importer/importer/worker.py
hrflow_importer/utils/__init__.py
hrflow_importer/utils/file_handler.py
hrflow_importer/utils/config/__init__.py
hrflow_importer/utils/config/config.py
hrflow_importer-0.2.1.dist-info/AUTHORS.rst
hrflow_importer-0.2.1.dist-info/LICENSE
hrflow_importer-0.2.1.dist-info/METADATA
hrflow_importer-0.2.1.dist-info/WHEEL
hrflow_importer-0.2.1.dist-info/entry_points.txt
hrflow_importer-0.2.1.dist-info/top_level.txt
hrflow_importer-0.2.1.dist-info/RECORD
