Metadata-Version: 2.1
Name: hrflow-importer
Version: 0.2.1
Summary: A python package for batch import of resume attachments to be parsed in HrFlow.
Home-page: https://github.com/Riminder/hrflow-importer
Author: HrFlow
Author-email: support+hrflow_importer@hrflow.ai
License: UNKNOWN
Project-URL: Documentation, https://developers.hrflow.ai/
Platform: any
Classifier: Development Status :: 4 - Beta
Classifier: Programming Language :: Python
Classifier: Programming Language :: Python :: 3.6
Requires-Python: >=3.6
License-File: LICENSE
License-File: AUTHORS.rst
Requires-Dist: hrflow (==1.9.0)
Requires-Dist: tqdm (==4.62.3)
Requires-Dist: typer (==0.4.0)
Requires-Dist: importlib-metadata ; python_version < "3.8"
Provides-Extra: testing
Requires-Dist: setuptools ; extra == 'testing'
Requires-Dist: pytest ; extra == 'testing'
Requires-Dist: pytest-cov ; extra == 'testing'
